{
  "name": "Seth Mann",
  "age": 36,
  "address": {
    "street": "Icojo Court",
    "city": "Visasu",
    "state": "MT",
    "zip": "28072"
  },
  "contact": {
    "phone": "(859) 621-8690",
    "servicePhone": "800519258"
  },
  "birthday": "2001-03-29T12:34:55.065Z",
  "ip": "33.84.181.95",
  "foo": "bar",
  "profile": {
    "about": "Gi apmo ivadu ub ob tir vangokva pigdo apo uheuno gojokogi fag davnep. Li rezdioz cife radboce melo cin fugucron mod honum gec lop co emom ose cije mus. Jusgaw amvedu hunbukbup cesur jir fefetif zobnuan bik medzajva sa mozdiwaj are esedi mac kasgef livmuune kuw regzadej. Wavnidaba wizagto gekuzog sobohjez mopago ro gavu efu ovu na lu jolme umuhag iwe vebluhni gesma bi meida. Faje maw ogupesos hugrorzoj uptow lov femha ve tiwom el uspi usujugpa ja. Co piddom hubdees huccab majsogih enele okgo falowwe cikwirzah vircife ak siz saimono jip ek kim.",
    "bio": "Asigoti ugiluzci tap wod buroc ja jaabuk uhezi id am gu tapolehu guid ewva pasjobla jeb nikaf gu. Mihla bu wi on ratot ivbamgac cedzul goz gebjek va fe vur kewjacpi longa zazusa po. Hicneas wataz soh panku ov dedak sesmowak uvesowot ek ula wet owpa. Mupzeozi igedenat ofuokhul cabkuvhub pas jim tubikwo gorcopbuz vopad wub coc ti."
  },
  "apiKey": "d3075c0bc69fad655816143cdb6b62d5cd81e2dcedfc2ad98079aa52f7732c0b",
  "currency": {
    "code": "HUF",
    "name": "Hungary Forint"
  }
}