{
  "name": "Antonio Crawford",
  "age": 54,
  "address": {
    "street": "Isvad Drive",
    "city": "Fikegikut",
    "state": "CO",
    "zip": "15808"
  },
  "contact": {
    "phone": "(238) 989-9045",
    "servicePhone": "800964853"
  },
  "birthday": "1998-02-21T20:53:41.195Z",
  "ip": "241.156.221.89",
  "foo": "bar",
  "profile": {
    "about": "Repoan movdotral ufepa riacewab tiv pib silfiha gez pimi bioh kasa uggouve haomohul cirowwoz ze puc. Hu wuhuzib jum walbuunu mowcej itjook ju bum nimaltur zimjam zojreluc wi. Ewa degizis voptif uce docuwhej lol fef encu juluti esiuridec jevipu zufakaf. Funmous fefen voijarec locu timkoh bajnu pacob fobi put ot mopwa ajilu gecjacu sob datwa.",
    "bio": "Ulugid ahun ga gos cudhe nilve ju te gij ovelihdo gepvesas ner nergada ciodto piwopofav wifagwud. Eki ig zi seirobu pamaci ucozibawu ec bokudeg mu bu zak alaihueg gitoc jetca ze rab. Joedu okenir aknachoc kiljotsu kafvawgo hosej luripizu voz ese jevpedpo nibbiral mesjijoz hifih zu re. Gucehja elu ar pi bohgeadi jagalkiw akuzubri uhnav tuecu dure von ivgushog bu fesmit lo baof war. Hakuzitu efo duvelwi sefev ice bo namosu ezlanram wizdor zupa rasatah so esla zener fuishoj ulu wefburbid. Bimzul lov dis hap buja jownisuz upru ihico avore ve ij pukkewtun ero."
  },
  "apiKey": "abb74c093fe92cf2def69afac16b2f86af4c1255c4eeebffc8e2843a02fac9b3",
  "currency": {
    "code": "JOD",
    "name": "Jordan Dinar"
  }
}