{
  "name": "Cora Cohen",
  "age": 42,
  "address": {
    "street": "Hotur Grove",
    "city": "Omevimca",
    "state": "DC",
    "zip": "20497"
  },
  "contact": {
    "phone": "(711) 303-6318",
    "servicePhone": "800881533"
  },
  "birthday": "1975-10-13T09:13:15.759Z",
  "ip": "53.56.154.142",
  "foo": "bar",
  "profile": {
    "about": "Gon jut vaitike az zez li uklutvuw gej za fenaeze onodur sifki zef. Dakeam dovvu perrurvup wo no ruzbizrip legcak dukesi he wolef areocacu covedjip pe. Iho wiv olpevla lajor wa vurras kud zovi golgil wecogzo si hocufso dof vebifin. Tuvar ekfe kih omaduw jabduvde kuvap inive wavvukal nonoltac dajekdu litube rur aguto osojitro zi mekowzi. Az elu vilji febawul webtuoz reka hiec ha goekuzuw susak nujiwmu hu nuevi.",
    "bio": "Vid bectanac sote hib ze sufate hagah zabid mezmongu fe dilcif jokfe. Id onwes zuh gen deldudus ilcotus cauteas howe izoli nagma forup uvzun bekuwa fo. Hug tu iserufsun wedbid iveelzo ratonfo mi zoda tozmisop jul ugjuca da. Uhirej ofkuko fiwowi soem bemser awvaf op gideru dejun pobipoc ulorefja rer miguj oba la hihlejzip."
  },
  "apiKey": "2d1c050a68eadea6dac025131df7541a0346c4a058643366ff25915617897fb5",
  "currency": {
    "code": "XAF",
    "name": "Communauté Financière Africaine (BEAC) CFA Franc BEAC"
  }
}