{
  "name": "Craig Gilbert",
  "age": 65,
  "address": {
    "street": "Evofas Glen",
    "city": "Motuzoj",
    "state": "DE",
    "zip": "92858"
  },
  "contact": {
    "phone": "(850) 423-8263",
    "servicePhone": "800579242"
  },
  "birthday": "2001-05-04T03:15:14.054Z",
  "ip": "126.23.96.11",
  "foo": "bar",
  "profile": {
    "about": "Miajow wem va ho dozed izujilimu hujmim jic hikileja dagavwav vuf fa hudpi tef it juh ku. Vedputvi egireno niloow binpap jouhrel huvudfi hacehiwof lu tupid receb lek bazam agaacme potek. Vitok funora ciwac ves poffod bet ihbuc nusjaweg ernos imiduvov duc cufoje se. Pom ciw mu iseboub losof cavanbik luzohos wunizza lemjujom utihel rovusa suwnok ivubibir vul homlehjo. Tovgoj ibfizalu aroikozi zarac povufga dit wumo janiej jiltudmuc sowuek dinhic aja uzguz newduha jahidel pacsekah tuvawu. Nozamvab bemaasa weh wujza cekadnen ku pujtonud faka ol fogic orlaf ga zidjuc waterupeh bused ubkarog cofoohi.",
    "bio": "Nutomci ec fe ne keaba iveosifa gevsub pislipco tiffoku do li agbigut. Se vubu sol memis gi kiim rugasih vidoswo cukpibop da povoze zapa. Le alebapjeb gubo wu rod cewbure hajumle hi wipmu vimukavi tir ob amo jerakha ag cuh vufatahop. Vobo porusose da iho epogepag gi dobav afopojef suralo ojro ger ok neti. Cizapsof ho uv toj mavrip aptuszu sucacsa it ganviwew fi vuthalti perafaes niz kebvuchu bofsalefu pev."
  },
  "apiKey": "cf26472824976d60e48413f61d64f725c44ba0a6d7130e8098183123c6c4a9eb",
  "currency": {
    "code": "HNL",
    "name": "Honduras Lempira"
  }
}